<?xml version="1.0" encoding="utf-8"?>
<SoundBanksInfo Platform="Windows" BasePlatform="Windows" SchemaVersion="12" SoundbankVersion="135">
	<RootPaths>
		<ProjectRoot>C:\coding\Arsonist-RoR2\ArsonistWWISE\</ProjectRoot>
		<SourceFilesRoot>C:\coding\Arsonist-RoR2\ArsonistWWISE\.cache\Windows\</SourceFilesRoot>
		<SoundBanksRoot>C:\coding\Arsonist-RoR2\ArsonistWWISE\GeneratedSoundBanks\Windows\</SoundBanksRoot>
		<ExternalSourcesInputFile></ExternalSourcesInputFile>
		<ExternalSourcesOutputRoot>C:\coding\Arsonist-RoR2\ArsonistWWISE\GeneratedSoundBanks\Windows</ExternalSourcesOutputRoot>
	</RootPaths>
	<DialogueEvents/>
	<StreamedFiles/>
	<MediaFilesNotInAnyBank/>
	<SoundBanks>
		<SoundBank Id="1110381487" Language="SFX" Hash="1662838081">
			<ObjectPath>\SoundBanks\Default Work Unit\arsonistSoundbank</ObjectPath>
			<ShortName>arsonistSoundbank</ShortName>
			<Path>arsonistSoundbank.bnk</Path>
			<IncludedEvents>
				<Event Id="1924783034" Name="Arsonist_Cleanse" ObjectPath="\Events\Default Work Unit\Arsonist_Cleanse">
					<IncludedMemoryFiles>
						<File Id="1035535129" Language="SFX">
							<ShortName>Cleanse - Shift\4. Cleanse.wav</ShortName>
							<Path>SFX\Cleanse - Shift\4. Cleanse_3F75BDB9.wem</Path>
						</File>
					</IncludedMemoryFiles>
				</Event>
				<Event Id="1840962711" Name="Arsonist_Masochism" ObjectPath="\Events\Default Work Unit\Arsonist_Masochism">
					<IncludedMemoryFiles>
						<File Id="381718716" Language="SFX">
							<ShortName>Special - Masochism\3. Masochism Laugh 3.wav</ShortName>
							<Path>SFX\Special - Masochism\3. Masochism Laugh 3_3F75BDB9.wem</Path>
						</File>
						<File Id="468282416" Language="SFX">
							<ShortName>Special - Masochism\1. Masochism Laugh 1.wav</ShortName>
							<Path>SFX\Special - Masochism\1. Masochism Laugh 1_3F75BDB9.wem</Path>
						</File>
						<File Id="597793787" Language="SFX">
							<ShortName>Special - Masochism\2. Masochism Laugh 2.wav</ShortName>
							<Path>SFX\Special - Masochism\2. Masochism Laugh 2_3F75BDB9.wem</Path>
						</File>
					</IncludedMemoryFiles>
				</Event>
				<Event Id="3408252638" Name="Arsonist_Overheat_Duration" ObjectPath="\Events\Default Work Unit\Arsonist_Overheat_Duration">
					<IncludedMemoryFiles>
						<File Id="1067383454" Language="SFX">
							<ShortName>Overheat\2. Overheat Duration.wav</ShortName>
							<Path>SFX\Overheat\2. Overheat Duration_9EDFC787.wem</Path>
						</File>
					</IncludedMemoryFiles>
				</Event>
				<Event Id="3787943995" Name="Arsonist_Overheat_Finish" ObjectPath="\Events\Default Work Unit\Arsonist_Overheat_Finish">
					<IncludedMemoryFiles>
						<File Id="20639472" Language="SFX">
							<ShortName>Overheat\3. Overheat Finish.wav</ShortName>
							<Path>SFX\Overheat\3. Overheat Finish_3F75BDB9.wem</Path>
						</File>
					</IncludedMemoryFiles>
				</Event>
				<Event Id="3152162514" Name="Arsonist_Overheat_Start" ObjectPath="\Events\Default Work Unit\Arsonist_Overheat_Start">
					<IncludedMemoryFiles>
						<File Id="752389951" Language="SFX">
							<ShortName>Overheat\1. Overheat Start.wav</ShortName>
							<Path>SFX\Overheat\1. Overheat Start_3F75BDB9.wem</Path>
						</File>
					</IncludedMemoryFiles>
				</Event>
				<Event Id="470984906" Name="Arsonist_Primary_Fire" ObjectPath="\Events\Default Work Unit\Arsonist_Primary_Fire">
					<IncludedMemoryFiles>
						<File Id="938389516" Language="SFX">
							<ShortName>Primary Fire\1. Primary Fire.wav</ShortName>
							<Path>SFX\Primary Fire\1. Primary Fire_3F75BDB9.wem</Path>
						</File>
					</IncludedMemoryFiles>
				</Event>
				<Event Id="2300744954" Name="Arsonist_Primary_Fire_Overheated" ObjectPath="\Events\Default Work Unit\Arsonist_Primary_Fire_Overheated">
					<IncludedMemoryFiles>
						<File Id="640021138" Language="SFX">
							<ShortName>Primary Fire\2. Primary Fire Overheated.wav</ShortName>
							<Path>SFX\Primary Fire\2. Primary Fire Overheated_3F75BDB9.wem</Path>
						</File>
					</IncludedMemoryFiles>
				</Event>
				<Event Id="3061346618" Name="Arsonist_Secondary_Flare_Explosion" ObjectPath="\Events\Default Work Unit\Arsonist_Secondary_Flare_Explosion">
					<IncludedMemoryFiles>
						<File Id="326243976" Language="SFX">
							<ShortName>Secondary Fire 1\2. Flare Explosion.wav</ShortName>
							<Path>SFX\Secondary Fire 1\2. Flare Explosion_3F75BDB9.wem</Path>
						</File>
					</IncludedMemoryFiles>
				</Event>
				<Event Id="3747272580" Name="Arsonist_Secondary_Flare_Projectile" ObjectPath="\Events\Default Work Unit\Arsonist_Secondary_Flare_Projectile">
					<IncludedMemoryFiles>
						<File Id="87249989" Language="SFX">
							<ShortName>Secondary Fire 1\1. Flare Projectile.wav</ShortName>
							<Path>SFX\Secondary Fire 1\1. Flare Projectile_3F75BDB9.wem</Path>
						</File>
					</IncludedMemoryFiles>
				</Event>
				<Event Id="1608533803" Name="Arsonist_Secondary_Flare_Projectile_Overheat" ObjectPath="\Events\Default Work Unit\Arsonist_Secondary_Flare_Projectile_Overheat">
					<IncludedMemoryFiles>
						<File Id="200903336" Language="SFX">
							<ShortName>Secondary Fire 1\3. Flare Projectile Overheat.wav</ShortName>
							<Path>SFX\Secondary Fire 1\3. Flare Projectile Overheat_3F75BDB9.wem</Path>
						</File>
					</IncludedMemoryFiles>
				</Event>
				<Event Id="3580806227" Name="Arsonist_Secondary_Flare_Punch" ObjectPath="\Events\Default Work Unit\Arsonist_Secondary_Flare_Punch">
					<IncludedMemoryFiles>
						<File Id="767924108" Language="SFX">
							<ShortName>1. Flare Punch.wav</ShortName>
							<Path>SFX\1. Flare Punch_3F75BDB9.wem</Path>
						</File>
					</IncludedMemoryFiles>
				</Event>
				<Event Id="1597575822" Name="Arsonist_Secondary_Flare_Punch_Contact" ObjectPath="\Events\Default Work Unit\Arsonist_Secondary_Flare_Punch_Contact">
					<IncludedMemoryFiles>
						<File Id="567405923" Language="SFX">
							<ShortName>Secondary Fire 2\3. Flare Punch Contact.wav</ShortName>
							<Path>SFX\Secondary Fire 2\3. Flare Punch Contact_3F75BDB9.wem</Path>
						</File>
					</IncludedMemoryFiles>
				</Event>
				<Event Id="2517450375" Name="Arsonist_Secondary_Flare_Punch_Explosion" ObjectPath="\Events\Default Work Unit\Arsonist_Secondary_Flare_Punch_Explosion">
					<IncludedMemoryFiles>
						<File Id="385415142" Language="SFX">
							<ShortName>Secondary Fire 2\2. Flare Explosion.wav</ShortName>
							<Path>SFX\Secondary Fire 2\2. Flare Explosion_3F75BDB9.wem</Path>
						</File>
					</IncludedMemoryFiles>
				</Event>
			</IncludedEvents>
			<GameParameters>
				<GameParameter Id="3673881719" Name="Volume_SFX" ObjectPath="\Game Parameters\Default Work Unit\Volume_SFX"/>
				<GameParameter Id="3695994288" Name="Volume_Master" ObjectPath="\Game Parameters\Default Work Unit\Volume_Master"/>
			</GameParameters>
		</SoundBank>
		<SoundBank Id="1355168291" Language="SFX" Hash="3701367528">
			<ObjectPath>Init</ObjectPath>
			<ShortName>Init</ShortName>
			<Path>Init.bnk</Path>
		</SoundBank>
	</SoundBanks>
</SoundBanksInfo>
